TileLangCXX
tilelang
