Metadata-Version: 2.4
Name: tilelang-rocm
Version: 0.1.4.post13
Summary: A tile level programming language to generate high performance code.
Home-page: https://github.com/tile-ai/tilelang
Author: Microsoft Research
License: MIT
Keywords: BLAS,CUDA,HIP,Code Generation,TVM
Platform: Environment :: GPU :: AMD ROCm
Platform: Operating System :: POSIX :: Linux
Classifier: Programming Language :: Python :: 3.8
Classifier: License :: OSI Approved :: MIT License
Classifier: Operating System :: OS Independent
Classifier: Intended Audience :: Developers
Classifier: Intended Audience :: Science/Research
Requires-Python: >=3.8
License-File: LICENSE
Requires-Dist: Cython
Requires-Dist: numpy>=1.23.5
Requires-Dist: tqdm>=4.62.3
Requires-Dist: typing_extensions>=4.10.0
Requires-Dist: cloudpickle
Requires-Dist: ml_dtypes
Requires-Dist: psutil
Requires-Dist: torch
Dynamic: author
Dynamic: classifier
Dynamic: description
Dynamic: description-content-type
Dynamic: home-page
Dynamic: keywords
Dynamic: license
Dynamic: license-file
Dynamic: platform
Dynamic: requires-dist
Dynamic: requires-python
Dynamic: summary
